flask_dropzone/__init__.py
flask_dropzone/utils.py
flask_dropzone/static/dropzone.min.css
flask_dropzone/static/dropzone.min.js
Flask_Dropzone-2.0.0.dist-info/LICENSE.txt
Flask_Dropzone-2.0.0.dist-info/METADATA
Flask_Dropzone-2.0.0.dist-info/WHEEL
Flask_Dropzone-2.0.0.dist-info/top_level.txt
Flask_Dropzone-2.0.0.dist-info/RECORD
