Metadata-Version: 2.1
Name: Flask-Dropzone
Version: 2.0.0
Summary: Upload files in Flask with Dropzone.js.
Home-page: https://github.com/helloflask/flask-dropzone
Author: Grey Li
Author-email: withlihui@gmail.com
License: MIT
Keywords: flask extension development upload
Platform: any
Classifier: Development Status :: 5 - Production/Stable
Classifier: Environment :: Web Environment
Classifier: Intended Audience :: Developers
Classifier: License :: OSI Approved :: MIT License
Classifier: Programming Language :: Python
Classifier: Programming Language :: Python :: 3
Classifier: Topic :: Internet :: WWW/HTTP :: Dynamic Content
Classifier: Topic :: Software Development :: Libraries :: Python Modules
License-File: LICENSE.txt
